setup.cfg
setup.py
pyswiss/__init__.py
pyswiss/classes.py
pyswiss/stack_trace.py
pyswiss.egg-info/PKG-INFO
pyswiss.egg-info/SOURCES.txt
pyswiss.egg-info/dependency_links.txt
pyswiss.egg-info/requires.txt
pyswiss.egg-info/top_level.txt