Metadata-Version: 1.1
Name: pyswiss
Version: 0.0.1
Summary: A collection of python tools and language insights.
Home-page: https://github.com/mathiasbc/pyswiss
Author: Mathias Bustamante
Author-email: mathiasbc@gmail.com
License: UNKNOWN
Download-URL: https://github.com/mathiasbc/pyswiss/tarball/0.0.1
Platform: UNKNOWN
